news_summerizer/__init__.py
news_summerizer/main.py
news_summerizer/prompts.py
news_summerizer-2025.12.20202646.dist-info/METADATA
news_summerizer-2025.12.20202646.dist-info/WHEEL
news_summerizer-2025.12.20202646.dist-info/top_level.txt
news_summerizer-2025.12.20202646.dist-info/RECORD
