Metadata-Version: 2.4
Name: news-summerizer
Version: 2025.12.20202646
Summary: A new package that processes news headlines or short text snippets to generate structured summaries. It takes a headline or brief news text as input and uses an LLM to extract key information such as 
Author-email: news-summerizer <hi@eugene.plus>
License: MIT
Project-URL: Homepage, https://github.com/chigwell/news-summerizer
Requires-Python: >=3.9
Requires-Dist: langchain-llm7>=0.0.0
Requires-Dist: llmatch-messages>=0.0.0
Requires-Dist: langchain-core>=0.3.0
